Workbook

Sheet Hypotheses
B1: TamCar - Budget 24 mois - HYPOTHESES (v3, option B : rester a 11 M)
B2: Discipline marketing stricte + ramp vehicules accelere. Valeurs verifiees.
B3: A - Productivite d'un vehicule
B4: Prix moyen d'une course | C4: 1500 | D4: Decision 2026-07
B5: Courses / jour / vehicule | C5: 10 | D5: Voiture & tricycle (moto = plus)
B6: Jours actifs / mois | C6: 26 | D6: Semaine de 6 jours
B7: Volume de courses / veh / mois | C7: 390000 | D7: =prix x courses x jours -> #NAME?
B8: B - Repartition (split 40/10/30/20)
B9: Part plateforme (directe) | C9: 0.2
B10: Part fonds rachat | C10: 0.1
B11: Part plateforme du rachat - An 1 | C11: 0.3 | D11: Degressif
B12: Part plateforme du rachat - An 2 | C12: 0.2 | D12: Degressif
B13: Assurance conducteur / veh / mois | C13: 500 | D13: Revenu TamCar
B14: Revenu plateforme / veh / mois - An 1 | C14: 90200 | D14: 20% vol + 30% rachat + assurance
B15: Revenu plateforme / veh / mois - An 2 | C15: 86300 | D15: 20% vol + 20% rachat + assurance
B16: C - Responsable Operations (NOUVEAU)
B17: Remuneration RO | C17: 3% des courses terminees | D17: Plancher 150 000 F/mois
B18: RO - cout total 24 mois | C18: 8441100 | D18: Variable, suit le volume
B19: D - Fiscalite & capital
B20: Impot sur les societes (IS) | C20: 0.3
B21: Retenue IRCM sur dividendes | C21: 0.1
B22: Taux de distribution dividendes | C22: 0.4
B23: Tresorerie de depart | C23: 11000000 | D23: Levee 10 M + reliquat (option B : inchangee)
B24: Capital social total | C24: 30000000 | D24: 20 M apport IP + 10 M numeraire
B25: Multiple de valorisation (sortie An 5) | C25: 5 | D25: x resultat net An 2

Sheet Recettes
B1: Recettes plateforme - 24 mois
B2: Ligne | C2: M1 | D2: M2 | E2: M3 | F2: M4 | G2: M5 | H2: M6 | I2: M7 | J2: M8 | K2: M9 | L2: M10 | M2: M11 | N2: M12 | O2: M13 | P2: M14 | Q2: M15 | R2: M16 | S2: M17 | T2: M18 | U2: M19 | V2: M20 | W2: M21 | X2: M22 | Y2: M23 | Z2: M24
B3: Vehicules actifs (INPUT bleu) | C3: 0 | D3: 4 | E3: 8 | F3: 12 | G3: 16 | H3: 20 | I3: 23 | J3: 26 | K3: 28 | L3: 30 | M3: 32 | N3: 34 | O3: 36 | P3: 38 | Q3: 40 | R3: 40 | S3: 40 | T3: 40 | U3: 40 | V3: 40 | W3: 40 | X3: 40 | Y3: 40 | Z3: 40
B4: Revenu / veh / mois | C4: 0 | D4: 90200 | E4: 90200 | F4: 90200 | G4: 90200 | H4: 90200 | I4: 90200 | J4: 90200 | K4: 90200 | L4: 90200 | M4: 90200 | N4: 90200 | O4: 86300 | P4: 86300 | Q4: 86300 | R4: 86300 | S4: 86300 | T4: 86300 | U4: 86300 | V4: 86300 | W4: 86300 | X4: 86300 | Y4: 86300 | Z4: 86300
B5: RECETTES PLATEFORME | C5: 0 | D5: =D3*D4 -> 360800 | E5: =E3*E4 -> 721600 | F5: =F3*F4 -> 1082400 | G5: =G3*G4 -> 1443200 | H5: =H3*H4 -> 1804000 | I5: =I3*I4 -> 2074600 | J5: =J3*J4 -> 2345200 | K5: =K3*K4 -> 2525600 | ... Z5: =Z3*Z4 -> 3452000
B7: Total An 1 (M1-M12) | C7: =SUM(C5:N5) -> 21016600
B8: Total An 2 (M13-M24) | C8: =SUM(O5:Z5) -> 40906200
B9: Total 24 mois | C9: =C7+C8 -> 61922800

Sheet Charges
B1: Charges - CAPEX + OPEX (v3 disciplinee)
B2: CAPEX de demarrage (M1)
B3: Formalisation societe (statuts+RCCM+IFU+annonce+valo App) | C3: 1500000
B4: ANATT - 1re autorisation + attestations + acomptes | C4: 666000
B5: Honoraires juriste OHADA (contrats) | C5: 300000
B6: Bureau - caution + amenagement | C6: 700000
B7: Materiel informatique + mobilier | C7: 1500000
B8: Marketing lancement (evenement, photo, video) [DISCIPLINE 1,0M] | C8: 1000000
B9: Charte visuelle + print + domaine/email | C9: 350000
B10: TOTAL CAPEX | C10: =SUM(C3:C9) -> 6016000
B12: OPEX mensuel | C12: M1 | D12: M2 | E12: M3 | F12: M4 | G12: M5 | H12: M6 | I12: M7 | J12: M8 | K12: M9 | L12: M10 | M12: M11 | N12: M12 | O12: M13 | P12: M14 | Q12: M15 | R12: M16 | S12: M17 | T12: M18 | U12: M19 | V12: M20 | W12: M21 | X12: M22 | Y12: M23 | Z12: M24
B13: Loyer | C13: 70000 | D13: 70000 | E13: 70000 | F13: 70000 | G13: 70000 | H13: 70000 | I13: 70000 | J13: 70000 | K13: 70000 | L13: 70000 | M13: 70000 | N13: 70000 | O13: 100000 | P13: 100000 | Q13: 100000 | R13: 100000 | S13: 100000 | T13: 100000 | U13: 100000 | V13: 100000 | W13: 100000 | X13: 100000 | Y13: 100000 | Z13: 100000
B14: Electricite et eau | C14: 70000 | D14: 70000 | E14: 70000 | F14: 70000 | G14: 70000 | H14: 70000 | I14: 70000 | J14: 70000 | K14: 70000 | L14: 70000 | M14: 70000 | N14: 70000 | O14: 100000 | P14: 100000 | Q14: 100000 | R14: 100000 | S14: 100000 | T14: 100000 | U14: 100000 | V14: 100000 | W14: 100000 | X14: 100000 | Y14: 100000 | Z14: 100000
B15: Supabase Pro | C15: 15000 | D15: 15000 | E15: 15000 | F15: 15000 | G15: 15000 | H15: 15000 | I15: 15000 | J15: 15000 | K15: 15000 | L15: 15000 | M15: 15000 | N15: 15000 | O15: 15000 | P15: 15000 | Q15: 15000 | R15: 15000 | S15: 15000 | T15: 15000 | U15: 15000 | V15: 15000 | W15: 15000 | X15: 15000 | Y15: 15000 | Z15: 15000
B16: Vercel Pro | C16: 15000 | D16: 15000 | E16: 15000 | F16: 15000 | G16: 15000 | H16: 15000 | I16: 15000 | J16: 15000 | K16: 15000 | L16: 15000 | M16: 15000 | N16: 15000 | O16: 15000 | P16: 15000 | Q16: 15000 | R16: 15000 | S16: 15000 | T16: 15000 | U16: 15000 | V16: 15000 | W16: 15000 | X16: 15000 | Y16: 15000 | Z16: 15000
B17: Mapbox | C17: 25000 | D17: 25000 | E17: 25000 | F17: 25000 | G17: 25000 | H17: 25000 | I17: 25000 | J17: 25000 | K17: 25000 | L17: 25000 | M17: 25000 | N17: 25000 | O17: 25000 | P17: 25000 | Q17: 25000 | R17: 25000 | S17: 25000 | T17: 25000 | U17: 25000 | V17: 25000 | W17: 25000 | X17: 25000 | Y17: 25000 | Z17: 25000
B18: Twilio SMS | C18: 25000 | D18: 25000 | E18: 25000 | F18: 25000 | G18: 25000 | H18: 25000 | I18: 25000 | J18: 25000 | K18: 25000 | L18: 25000 | M18: 25000 | N18: 25000 | O18: 25000 | P18: 25000 | Q18: 25000 | R18: 25000 | S18: 25000 | T18: 25000 | U18: 25000 | V18: 25000 | W18: 25000 | X18: 25000 | Y18: 25000 | Z18: 25000
B19: IA Vision | C19: 10000 | D19: 10000 | E19: 10000 | F19: 10000 | G19: 10000 | H19: 10000 | I19: 10000 | J19: 10000 | K19: 10000 | L19: 10000 | M19: 10000 | N19: 10000 | O19: 10000 | P19: 10000 | Q19: 10000 | R19: 10000 | S19: 10000 | T19: 10000 | U19: 10000 | V19: 10000 | W19: 10000 | X19: 10000 | Y19: 10000 | Z19: 10000
B20: Claude Code | C20: 65000 | D20: 65000 | E20: 65000 | F20: 65000 | G20: 65000 | H20: 65000 | I20: 65000 | J20: 65000 | K20: 65000 | L20: 65000 | M20: 65000 | N20: 65000 | O20: 65000 | P20: 65000 | Q20: 65000 | R20: 65000 | S20: 65000 | T20: 65000 | U20: 65000 | V20: 65000 | W20: 65000 | X20: 65000 | Y20: 65000 | Z20: 65000
B21: Domaine pro + email pro | C21: 2500 | D21: 2500 | E21: 2500 | F21: 2500 | G21: 2500 | H21: 2500 | I21: 2500 | J21: 2500 | K21: 2500 | L21: 2500 | M21: 2500 | N21: 2500 | O21: 2500 | P21: 2500 | Q21: 2500 | R21: 2500 | S21: 2500 | T21: 2500 | U21: 2500 | V21: 2500 | W21: 2500 | X21: 2500 | Y21: 2500 | Z21: 2500
B22: Secretaire | C22: 100000 | D22: 100000 | E22: 100000 | F22: 100000 | G22: 100000 | H22: 100000 | I22: 100000 | J22: 100000 | K22: 100000 | L22: 100000 | M22: 100000 | N22: 100000 | O22: 100000 | P22: 100000 | Q22: 100000 | R22: 100000 | S22: 100000 | T22: 100000 | U22: 100000 | V22: 100000 | W22: 100000 | X22: 100000 | Y22: 100000 | Z22: 100000
B23: Community manager | C23: 75000 | D23: 75000 | E23: 75000 | F23: 75000 | G23: 75000 | H23: 75000 | I23: 75000 | J23: 75000 | K23: 75000 | L23: 75000 | M23: 75000 | N23: 75000 | O23: 75000 | P23: 75000 | Q23: 75000 | R23: 75000 | S23: 75000 | T23: 75000 | U23: 75000 | V23: 75000 | W23: 75000 | X23: 75000 | Y23: 75000 | Z23: 75000
B24: Comptable externe | C24: 75000 | D24: 75000 | E24: 75000 | F24: 75000 | G24: 75000 | H24: 75000 | I24: 75000 | J24: 75000 | K24: 75000 | L24: 75000 | M24: 75000 | N24: 75000 | O24: 75000 | P24: 75000 | Q24: 75000 | R24: 75000 | S24: 75000 | T24: 75000 | U24: 75000 | V24: 75000 | W24: 75000 | X24: 75000 | Y24: 75000 | Z24: 75000
... B32: Parrainage (bonus 500 F) | C32: 100000 | D32: 100000 | E32: 100000 | F32: 0 | G32: 0 | H32: 0 | I32: 0 | J32: 0 | K32: 0 | L32: 100000 | M32: 100000 | N32: 100000 | O32: 100000 | P32: 100000 | Q32: 100000 | R32: 100000 | S32: 100000 | T32: 100000 | U32: 100000 | V32: 100000 | W32: 100000 | X32: 100000 | Y32: 100000 | Z32: 100000
B33: TOTAL OPEX MENSUEL | C33: =SUM(C13:C32) -> 1204500 | D33: =SUM(D13:D32) -> 1354500 | E33: =SUM(E13:E32) -> 1354500 | F33: =SUM(F13:F32) -> 1254500 | G33: =SUM(G13:G32) -> 1254500 | H33: =SUM(H13:H32) -> 1254500 | I33: =SUM(I13:I32) -> 1054500 | J33: =SUM(J13:J32) -> 1054500 | ... Z33: =SUM(Z13:Z32) -> 1369500
B35: OPEX An 1 (12 mois) | C35: =SUM(C33:N33) -> 14304000
B36: OPEX An 2 (12 mois) | C36: =SUM(O33:Z33) -> 15434000

Sheet P&L 24 mois
B1: P&L consolide - 24 mois (v3)
B2: Poste | C2: M1 | D2: M2 | E2: M3 | F2: M4 | G2: M5 | H2: M6 | I2: M7 | J2: M8 | K2: M9 | L2: M10 | M2: M11 | N2: M12 | O2: M13 | P2: M14 | Q2: M15 | R2: M16 | S2: M17 | T2: M18 | U2: M19 | V2: M20 | W2: M21 | X2: M22 | Y2: M23 | Z2: M24
B3: Recettes plateforme | C3: 0 | D3: =Recettes!D5 -> 360800 | E3: =Recettes!E5 -> 721600 | F3: =Recettes!F5 -> 1082400 | G3: =Recettes!G5 -> 1443200 | H3: =Recettes!H5 -> 1804000 | I3: =Recettes!I5 -> 2074600 | J3: =Recettes!J5 -> 2345200 | K3: =Recettes!K5 -> 2525600 | ... Z3: =Recettes!Z5 -> 3452000
B4: CAPEX (M1) | C4: =Charges!C10 -> 6016000 | D4: 0 | E4: 0 | F4: 0 | G4: 0 | H4: 0 | I4: 0 | J4: 0 | K4: 0 | L4: 0 | M4: 0 | N4: 0 | O4: 0 | P4: 0 | Q4: 0 | R4: 0 | S4: 0 | T4: 0 | U4: 0 | V4: 0 | W4: 0 | X4: 0 | Y4: 0 | Z4: 0
B5: OPEX recurrent | C5: =Charges!C33 -> 1204500 | D5: =Charges!D33 -> 1354500 | E5: =Charges!E33 -> 1354500 | F5: =Charges!F33 -> 1254500 | G5: =Charges!G33 -> 1254500 | H5: =Charges!H33 -> 1254500 | I5: =Charges!I33 -> 1054500 | J5: =Charges!J33 -> 1054500 | ... Z5: =Charges!Z33 -> 1369500
B6: Resultat avant impot | C6: =C4+C5 -> 7220500 | D6: =D4+D5 -> 1354500 | E6: =E4+E5 -> 1354500 | F6: =F4+F5 -> 1254500 | G6: =G4+G5 -> 1254500 | H6: =H4+H5 -> 1254500 | I6: =I4+I5 -> 1054500 | J6: =J4+J5 -> 1054500 | ... Z6: =Z4+Z5 -> 1369500
B7: Tresorerie debut de mois | C7: 10000000 | D7: =C8+D3 -> 3140300 | E7: =D8+E3 -> 2507400 | F7: =E8+F3 -> 2235300 | G7: =F8+G3 -> 2424000 | H7: =G8+H3 -> 2973500 | I7: =H8+I3 -> 3793600 | J7: =I8+J3 -> 5084300 | K7: =J8+K3 -> 6555400 | ... Z7: =Y8+Z3 -> 37538300
B8: Tresorerie fin de mois | C8: =C7-C6 -> 2779500 | D8: =D7-D6 -> 1785800 | E8: =E7-E6 -> 1152900 | F8: =F7-F6 -> 980800 | G8: =G7-G6 -> 1169500 | H8: =H7-H6 -> 1719000 | I8: =I7-I6 -> 2739100 | J8: =J7-J6 -> 4029800 | ... Z8: =Z7-Z6 -> 36168800
B11: SYNTHESE
B12: Recettes An 1 | C12: =Recettes!C7 -> 21016600
B13: Recettes An 2 | C13: =Recettes!C8 -> 40906200
B14: Charges An 1 (CAPEX+OPEX) | C14: =Charges!C35 -> 14304000
B15: Charges An 2 | C15: =Charges!C36 -> 15434000
B16: Resultat An 1 | C16: =C12-C14 -> 6712600
B17: Resultat An 2 avant IS | C17: =C13-C15 -> 25472200
B18: IS An 2 (30%) | C18: =C17*0.3 -> 7641660
B19: RESULTAT NET An 2 | C19: =C17-C16-C18 -> 11117940
B20: Creux de tresorerie | C20: 0
B21: (au mois) | C21: -
B22: Tresorerie fin M24 | C22: =Z8 -> 36168800

Sheet Investisseur
B1: Rendement investisseur - ticket 1 M FCFA (v3)
B2: Part au capital | C2: 0.033333333
B3: Resultat net An 2 | C3: ='P&L 24 mois'!C19 -> 11117940
B4: Dividendes An 2 (40%) | C4: 5635392
B5: Part investisseur (brut) | C5: 187846.4
B6: Dividende net IRCM | C6: 169061.76
B7: Dividendes nets cumules ~5 ans | C7: 591716.16
B8: Valeur societe a la sortie | C8: 70442400
B9: Valeur du ticket a la sortie | C9: 2348080
B10: Ticket de depart | C10: 1000000
B11: RETOUR TOTAL (div + plus-value) | C11: 2939796.2
B12: RETOUR NET (gain) | C12: 1939796.2
B13: RETOUR en % du ticket | C13: 1.9397962
