Workbook

Sheet Hypothèses
B2: TamCar — Budget 24 mois · HYPOTHÈSES
B3: Édition 2026-07 · Modifie UNIQUEMENT les cellules bleues, tout le reste se recalcule.
B5: A · Productivité d'un véhicule (scénario réaliste)
B6: Prix moyen d'une course | C6: 1500 | D6: Décision 2026-07 (au lieu de 2 500)
B7: Courses / jour / véhicule | C7: 10 | D7: Voiture & tricycle (moto = plus)
B8: Jours actifs / mois | C8: 26 | D8: Semaine de 6 jours (dimanche off)
B9: Volume de courses / véh / mois | C9: =C6*C7*C8 | D9: Calculé = prix × courses × jours
B11: B · Répartition de chaque course (split 40/10/30/20)
B12: Part plateforme (directe) | C12: 0.2 | D12: Revenu TamCar par course
B13: Part fonds rachat | C13: 0.1 | D13: Alimente le rachat véhicule
B14: Part plateforme du fonds rachat — An 1 | C14: 0.3 | D14: Dégressif
B15: Part plateforme du fonds rachat — An 2 | C15: 0.2 | D15: Dégressif
B16: Assurance conducteur / véh / mois | C16: 2000 | D16: Prélèvement mensuel (revenu TamCar)
B17: Revenu plateforme / véh / mois — An 1 | C17: =C9*C12 + C9*C13*C14 + C16 | D17: 20% volume + 30% du rachat + assurance
B18: Revenu plateforme / véh / mois — An 2 | C18: =C9*C12 + C9*C13*C15 + C16 | D18: 20% volume + 20% du rachat + assurance
B20: C · Fiscalité & capital
B21: Impôt sur les sociétés (IS) | C21: 0.3 | D21: Sur résultat annuel positif
B22: Retenue IRCM sur dividendes | C22: 0.1 | D22: Prélevée à la distribution
B23: Taux de distribution des dividendes | C23: 0.4 | D23: % du résultat net distribué
B24: Trésorerie de départ | C24: 11000000 | D24: Levée 10 M + reliquat CAPEX
B25: Capital social total | C25: 30000000 | D25: 20 M apport IP + 10 M numéraire
B26: Ticket investisseur (référence) | C26: 1000000 | D26: Pour le calcul de rendement
B27: Multiple de valorisation à la sortie (An 5) | C27: 5 | D27: Valeur société = multiple × résultat net An 2
B29: Note : la trajectoire mensuelle des véhicules actifs est saisie dans l'onglet « Recettes » (ligne bleue).

Sheet Recettes
B2: Recettes plateforme — 24 mois
B4: Ligne | C4: M1 | D4: M2 | E4: M3 | F4: M4 | G4: M5 | H4: M6 | I4: M7 | J4: M8 | K4: M9 | L4: M10 | M4: M11 | N4: M12 | O4: M13 | P4: M14 | Q4: M15 | R4: M16 | S4: M17 | T4: M18 | U4: M19 | V4: M20 | W4: M21 | X4: M22 | Y4: M23 | Z4: M24
B5: Véhicules actifs | C5: 0 | D5: 0 | E5: 3 | F5: 5 | G5: 7 | H5: 10 | I5: 12 | J5: 13 | K5: 15 | L5: 17 | M5: 20 | N5: 25 | O5: 25 | P5: 26 | Q5: 27 | R5: 28 | S5: 29 | T5: 30 | U5: 30 | V5: 30 | W5: 30 | X5: 30 | Y5: 30 | Z5: 30
B6: Revenu / véh / mois | C6: ='Hypothèses'!$C$17 | D6: ='Hypothèses'!$C$17 | E6: ='Hypothèses'!$C$17 | F6: ='Hypothèses'!$C$17 | G6: ='Hypothèses'!$C$17 | H6: ='Hypothèses'!$C$17 | I6: ='Hypothèses'!$C$17 | J6: ='Hypothèses'!$C$17 | ... N6: ='Hypothèses'!$C$17 | O6: ='Hypothèses'!$C$18 | P6: ='Hypothèses'!$C$18 | Q6: ='Hypothèses'!$C$18 | R6: ='Hypothèses'!$C$18 | S6: ='Hypothèses'!$C$18 | T6: ='Hypothèses'!$C$18 | U6: ='Hypothèses'!$C$18 | V6: ='Hypothèses'!$C$18 | ... Z6: ='Hypothèses'!$C$18
B7: RECETTES PLATEFORME | C7: =C5*C6 | D7: =D5*D6 | E7: =E5*E6 | F7: =F5*F6 | G7: =G5*G6 | H7: =H5*H6 | I7: =I5*I6 | J7: =J5*J6 | ... Z7: =Z5*Z6
B9: Total An 1 (M1-M12) | C9: =SUM(C7:N7)
B10: Total An 2 (M13-M24) | C10: =SUM(O7:Z7)
B11: Total 24 mois | C11: =C9+C10

Sheet Charges
B2: Charges — CAPEX (démarrage) + OPEX mensuel
B4: CAPEX de démarrage (one-shot, imputé M1)
B5: Notaire — constitution SARL | C5: 350000
B6: RCCM + IFU + annonce légale + compte pro | C6: 115000
B7: ANATT — 1re autorisation + attestations + acomptes | C7: 666000
B8: Honoraires juriste OHADA (contrats) | C8: 800000
B9: Commissaire aux apports | C9: 750000
B10: Bureau — caution + aménagement | C10: 700000
B11: Matériel informatique + mobilier | C11: 700000
B12: Marketing lancement (événement, photo, vidéo) | C12: 900000
B13: Habillage 10 véhicules + inspections + kits | C13: 460000
B14: Charte visuelle + print + domaine/email | C14: 175000
B15: TOTAL CAPEX | C15: =SUM(C5:C14)
B17: OPEX mensuel par catégorie
B18: Catégorie | C18: M1 | D18: M2 | E18: M3 | F18: M4 | G18: M5 | H18: M6 | I18: M7 | J18: M8 | K18: M9 | L18: M10 | M18: M11 | N18: M12 | O18: M13 | P18: M14 | Q18: M15 | R18: M16 | S18: M17 | T18: M18 | U18: M19 | V18: M20 | W18: M21 | X18: M22 | Y18: M23 | Z18: M24
B19: Bureau & infrastructure | C19: 200000 | D19: 200000 | E19: 200000 | F19: 200000 | G19: 200000 | H19: 200000 | I19: 200000 | J19: 200000 | K19: 200000 | L19: 200000 | M19: 200000 | N19: 200000 | O19: 200000 | P19: 200000 | Q19: 200000 | R19: 200000 | S19: 200000 | T19: 200000 | U19: 200000 | V19: 200000 | W19: 200000 | X19: 200000 | Y19: 200000 | Z19: 200000
B20: Tech (Supabase, Vercel, Mapbox, SMS, IA) | C20: 84000 | D20: 84000 | E20: 84000 | F20: 84000 | G20: 84000 | H20: 84000 | I20: 84000 | J20: 84000 | K20: 84000 | L20: 84000 | M20: 84000 | N20: 84000 | O20: 83500 | P20: 83500 | Q20: 83500 | R20: 83500 | S20: 83500 | T20: 83500 | U20: 83500 | V20: 83500 | W20: 83500 | X20: 83500 | Y20: 83500 | Z20: 83500
B21: RH externalisée (support, CM, compta, juriste) | C21: 275000 | D21: 275000 | E21: 275000 | F21: 275000 | G21: 275000 | H21: 275000 | I21: 275000 | J21: 275000 | K21: 275000 | L21: 275000 | M21: 275000 | N21: 275000 | O21: 275000 | P21: 275000 | Q21: 275000 | R21: 275000 | S21: 275000 | T21: 275000 | U21: 275000 | V21: 275000 | W21: 275000 | X21: 275000 | Y21: 275000 | Z21: 275000
B22: Marketing & acquisition | C22: 450000 | D22: 450000 | E22: 450000 | F22: 450000 | G22: 450000 | H22: 450000 | I22: 450000 | J22: 450000 | K22: 450000 | L22: 450000 | M22: 450000 | N22: 450000 | O22: 750000 | P22: 750000 | Q22: 750000 | R22: 750000 | S22: 750000 | T22: 750000 | U22: 750000 | V22: 750000 | W22: 750000 | X22: 750000 | Y22: 750000 | Z22: 750000
B23: Financier & Mobile Money + assurance RC | C23: 77000 | D23: 77000 | E23: 77000 | F23: 77000 | G23: 77000 | H23: 77000 | I23: 77000 | J23: 77000 | K23: 77000 | L23: 77000 | M23: 77000 | N23: 77000 | O23: 82000 | P23: 82000 | Q23: 82000 | R23: 82000 | S23: 82000 | T23: 82000 | U23: 82000 | V23: 82000 | W23: 82000 | X23: 82000 | Y23: 82000 | Z23: 82000
B24: Ops manager (dès M18) | C24: 0 | D24: 0 | E24: 0 | F24: 0 | G24: 0 | H24: 0 | I24: 0 | J24: 0 | K24: 0 | L24: 0 | M24: 0 | N24: 0 | O24: 0 | P24: 0 | Q24: 0 | R24: 0 | S24: 0 | T24: 200000 | U24: 200000 | V24: 200000 | W24: 200000 | X24: 200000 | Y24: 200000 | Z24: 200000
B25: Extension Parakou (dès M18) | C25: 0 | D25: 0 | E25: 0 | F25: 0 | G25: 0 | H25: 0 | I25: 0 | J25: 0 | K25: 0 | L25: 0 | M25: 0 | N25: 0 | O25: 0 | P25: 0 | Q25: 0 | R25: 0 | S25: 0 | T25: 125000 | U25: 125000 | V25: 125000 | W25: 125000 | X25: 125000 | Y25: 125000 | Z25: 125000
B26: TOTAL OPEX MENSUEL | C26: =SUM(C19:C25) | D26: =SUM(D19:D25) | E26: =SUM(E19:E25) | F26: =SUM(F19:F25) | G26: =SUM(G19:G25) | H26: =SUM(H19:H25) | I26: =SUM(I19:I25) | J26: =SUM(J19:J25) | ... Z26: =SUM(Z19:Z25)

Sheet P&L 24 mois
B2: P&L consolidé — 24 mois
B4: Poste | C4: M1 | D4: M2 | E4: M3 | F4: M4 | G4: M5 | H4: M6 | I4: M7 | J4: M8 | K4: M9 | L4: M10 | M4: M11 | N4: M12 | O4: M13 | P4: M14 | Q4: M15 | R4: M16 | S4: M17 | T4: M18 | U4: M19 | V4: M20 | W4: M21 | X4: M22 | Y4: M23 | Z4: M24
B5: Recettes plateforme | C5: =Recettes!C7 | D5: =Recettes!D7 | E5: =Recettes!E7 | F5: =Recettes!F7 | G5: =Recettes!G7 | H5: =Recettes!H7 | I5: =Recettes!I7 | J5: =Recettes!J7 | ... Z5: =Recettes!Z7
B6: CAPEX (M1) | C6: =-Charges!$C$15 | D6: 0 | E6: 0 | F6: 0 | G6: 0 | H6: 0 | I6: 0 | J6: 0 | K6: 0 | L6: 0 | M6: 0 | N6: 0 | O6: 0 | P6: 0 | Q6: 0 | R6: 0 | S6: 0 | T6: 0 | U6: 0 | V6: 0 | W6: 0 | X6: 0 | Y6: 0 | Z6: 0
B7: OPEX récurrent | C7: =-Charges!C26 | D7: =-Charges!D26 | E7: =-Charges!E26 | F7: =-Charges!F26 | G7: =-Charges!G26 | H7: =-Charges!H26 | I7: =-Charges!I26 | J7: =-Charges!J26 | ... Z7: =-Charges!Z26
B8: Résultat avant impôt | C8: =C5+C6+C7 | D8: =D5+D6+D7 | E8: =E5+E6+E7 | F8: =F5+F6+F7 | G8: =G5+G6+G7 | H8: =H5+H6+H7 | I8: =I5+I6+I7 | J8: =J5+J6+J7 | ... Z8: =Z5+Z6+Z7
B10: Trésorerie début de mois | C10: ='Hypothèses'!$C$24 | D10: =C11 | E10: =D11 | F10: =E11 | G10: =F11 | H10: =G11 | I10: =H11 | J10: =I11 | K10: =J11 | ... Z10: =Y11
B11: Trésorerie fin de mois | C11: =C10+C8 | D11: =D10+D8 | E11: =E10+E8 | F11: =F10+F8 | G11: =G10+G8 | H11: =H10+H8 | I11: =I10+I8 | J11: =J10+J8 | ... Z11: =Z10+Z8
B13: Synthèse
B14: Recettes An 1 | C14: =SUM(C5:N5)
B15: Recettes An 2 | C15: =SUM(O5:Z5)
B16: Charges An 1 (CAPEX+OPEX) | C16: =-SUM(C6:N7)
B17: Charges An 2 | C17: =-SUM(O6:Z7)
B18: Résultat avant impôt An 1 | C18: =C14-C16
B19: Résultat avant impôt An 2 | C19: =C15-C17
B20: IS An 2 (30% si positif) | C20: =-'Hypothèses'!$C$21*MAX(0,C19)
B21: Résultat NET An 2 | C21: =C19+C20
B23: Trésorerie fin M12 | C23: =N11
B24: Trésorerie fin M24 | C24: =Z11

Sheet Investisseur
B2: Rendement investisseur — ticket 1 M FCFA
B3: Basé sur le P&L ci-contre (prix course 1 500 F). Hypothèse conservatrice.
B5: Part de l'investisseur au capital | C5: ='Hypothèses'!$C$26/'Hypothèses'!$C$25 | D5: 1 M / 30 M
B7: Résultat net An 2 (société) | C7: ='P&L 24 mois'!C21 | D7: Après IS
B8: Dividendes distribués An 2 (40%) | C8: ='Hypothèses'!$C$23*MAX(0,'P&L 24 mois'!C21) | D8: Si résultat positif
B9: Part de l'investisseur (brut) | C9: =C5*C8 | D9: Sa quote-part
B10: Dividende net d'IRCM (An 2) | C10: =C9*(1-'Hypothèses'!$C$22) | D10: Après retenue 10%
B12: Dividendes nets cumulés ~5 ans | C12: =C10*3.5 | D12: Hyp. An3-5 ≈ 3,5× l'An 2 (croissance)
B14: Valeur de la société à la sortie | C14: ='Hypothèses'!$C$27*MAX(0,'P&L 24 mois'!C21) | D14: Multiple × résultat net An 2
B15: Valeur du ticket à la sortie | C15: =C5*C14 | D15: Quote-part de l'investisseur
B17: Ticket de départ | C17: ='Hypothèses'!$C$26
B18: RETOUR TOTAL (dividendes + plus-value) | C18: =C12+C15 | D18: Sur ~5 ans
B19: RETOUR en % du ticket | C19: =(C12+C15)/C17-1
B21: ⚠️ Chiffres pilotés par les Hypothèses. La valorisation à la sortie dépend fortement du multiple (C27) et du résultat An 2 — à challenger avec un CFO.
