Workbook

Sheet Actionnaires
A1: TamCar SARL — Registre des actionnaires
A2: Valeur nominale part : 10 000 FCFA · IP fondateur : 20 000 000 FCFA · Min concessionnaire : 500 000 F · Min investisseur : 1 000 000 F
A4: Nom complet | B4: Type | C4: Statut | D4: Véhicule apporté | E4: Valeur véhicule (indic.) F | F4: Cash au capital (F) | G4: Parts | H4: % capital | I4: ADR versé (100k × véh.) | J4: Téléphone / Email
A5: Terence Beni Raphaël QUENUM | B5: Fondateur (IP) | C5: Confirmé | D5: — | E5: — | F5: 20000000 | G5: =F5/10000 | H5: =IFERROR(G5/G$26,"") | I5: — | J5: terencebeniraphael@gmail.com
A6: Ex : Jean K. | B6: Concessionnaire | C6: Prospect | D6: Essentiel (Toyota Yaris) | E6: 3000000 | F6: 500000 | G6: =IF(ISNUMBER(F6),F6/10000,"") | H6: =IFERROR(G6/G$26,"") | I6: 100000 | J6: +229 61 XX XX XX
A7: Ex : Marie A. | B7: Concessionnaire | C7: LOI signé | D7: Confort (Corolla) | E7: 4500000 | F7: 800000 | G7: =IF(ISNUMBER(F7),F7/10000,"") | H7: =IFERROR(G7/G$26,"") | I7: 100000 | J7: +229 62 XX XX XX
A8: Ex : Paul D. | B8: Investisseur | C8: Cash versé | D8: — | F8: 3000000 | G8: =IF(ISNUMBER(F8),F8/10000,"") | H8: =IFERROR(G8/G$26,"") | J8: +229 65 XX XX XX
A9: Ex : Cousin | B9: Investisseur | C9: Prospect | D9: — | F9: 1500000 | G9: =IF(ISNUMBER(F9),F9/10000,"") | H9: =IFERROR(G9/G$26,"")
G10: =IF(ISNUMBER(F10),F10/10000,"") | H10: =IFERROR(G10/G$26,"")
G11: =IF(ISNUMBER(F11),F11/10000,"") | H11: =IFERROR(G11/G$26,"")
G12: =IF(ISNUMBER(F12),F12/10000,"") | H12: =IFERROR(G12/G$26,"")
G13: =IF(ISNUMBER(F13),F13/10000,"") | H13: =IFERROR(G13/G$26,"")
G14: =IF(ISNUMBER(F14),F14/10000,"") | H14: =IFERROR(G14/G$26,"")
G15: =IF(ISNUMBER(F15),F15/10000,"") | H15: =IFERROR(G15/G$26,"")
G16: =IF(ISNUMBER(F16),F16/10000,"") | H16: =IFERROR(G16/G$26,"")
G17: =IF(ISNUMBER(F17),F17/10000,"") | H17: =IFERROR(G17/G$26,"")
G18: =IF(ISNUMBER(F18),F18/10000,"") | H18: =IFERROR(G18/G$26,"")
G19: =IF(ISNUMBER(F19),F19/10000,"") | H19: =IFERROR(G19/G$26,"")
G20: =IF(ISNUMBER(F20),F20/10000,"") | H20: =IFERROR(G20/G$26,"")
G21: =IF(ISNUMBER(F21),F21/10000,"") | H21: =IFERROR(G21/G$26,"")
... G24: =IF(ISNUMBER(F24),F24/10000,"") | H24: =IFERROR(G24/G$26,"")
A26: TOTAL | F26: =SUM(F5:F24) | G26: =SUM(G5:G24) | H26: =IFERROR(SUM(H5:H24),"") | I26: =SUM(I5:I24)
A29: Mode d'emploi
A30: 1. La ligne 5 (fondateur) est fixe : ne pas modifier — apport IP 20 M FCFA = 2 000 parts.
A31: 2. Pour ajouter un souscripteur : va sur une ligne vide (6-24), remplis Nom, Type, Statut, Véhicule (si concessionnaire), Cash au capital, ADR, Contact.
A32: 3. Les colonnes 'Parts' et '% capital' se calculent automatiquement — ne pas les modifier.
A33: 4. Statut : Prospect → LOI signé → Cash versé → Confirmé.
A34: 5. Type : Concessionnaire (véhicule + min 500 k) OU Investisseur (cash pur min 1 M).
A35: 6. La valeur du véhicule est indicative — elle ne rentre PAS dans le capital (le véhicule reste ta propriété, exploité par TamCar via contrat).
A36: 7. ADR = 100 000 F par véhicule apporté, en compte courant associé (remboursable via revenus courses).

Sheet Tableau de bord
A1: TamCar SARL — Suivi levée capital
A3: Capital total (FCFA) | B3: ='Actionnaires'!F26+20000000
A4: dont IP fondateur | B4: =20000000
A5: dont cash levé | B5: ='Actionnaires'!F26-20000000
A6: Nombre total de parts | B6: ='Actionnaires'!G26
A7: % Terence (fondateur) | B7: =IFERROR(2000/'Actionnaires'!G26,"")
A8: Nombre d'actionnaires actifs | B8: =COUNTIF('Actionnaires'!C6:C24,"Cash versé")+COUNTIF('Actionnaires'!C6:C24,"Confirmé")+1
A9: ADR total (compte courant) | B9: ='Actionnaires'!I26
A12: Alertes contrôle Terence
A13: >= 51 % : contrôle absolu (majorité simple) | B13: =IF(IFERROR(2000/'Actionnaires'!G26,0)>=0.51,"OK — majorité absolue conservée","ATTENTION — Terence n'a plus la majorité")
A14: >= 60 % : super-marge de sécurité | B14: =IF(IFERROR(2000/'Actionnaires'!G26,0)>=0.60,"OK — position confortable","Zone modérée — vérifie tes objectifs")
A15: >= 67 % : super-majorité pour décisions extraordinaires | B15: =IF(IFERROR(2000/'Actionnaires'!G26,0)>=0.6667,"OK — décisions extraordinaires libres","Attention — tu dépends de tiers pour décisions extraordinaires")
A18: Répartition par catégorie
A19: Catégorie | B19: Nb associés | C19: Cash apporté (F) | D19: % capital
A20: Fondateur (IP) | B20: =1 | C20: =20000000 | D20: =IFERROR(2000/'Actionnaires'!G26,0)
A21: Concessionnaires | B21: =COUNTIF('Actionnaires'!B6:B24,"Concessionnaire") | C21: =SUMIF('Actionnaires'!B6:B24,"Concessionnaire",'Actionnaires'!F6:F24) | D21: =IFERROR(SUMIF('Actionnaires'!B6:B24,"Concessionnaire",'Actionnaires'!G6:G24)/'Actionnaires'!G26,0)
A22: Investisseurs | B22: =COUNTIF('Actionnaires'!B6:B24,"Investisseur") | C22: =SUMIF('Actionnaires'!B6:B24,"Investisseur",'Actionnaires'!F6:F24) | D22: =IFERROR(SUMIF('Actionnaires'!B6:B24,"Investisseur",'Actionnaires'!G6:G24)/'Actionnaires'!G26,0)

Sheet Règles
A1: Règles du capital TamCar SARL
A3: Valeur nominale d'une part sociale | B3: 10 000 FCFA
A4: Apport en nature Terence (IP TamCar) | B4: 20 000 000 FCFA = 2 000 parts (fixe)
A5: Minimum souscription Concessionnaire | B5: 500 000 F (50 parts) + 1 véhicule minimum
A6: Minimum souscription Investisseur passif | B6: 1 000 000 F (100 parts) — pas de véhicule requis
A7: Plafond individuel | B7: 20 % du capital (aucun associé seul ne peut dépasser)
A8: ADR (Avance Démarrage Remboursable) | B8: 100 000 F par véhicule apporté — en compte courant, hors capital
A9: Traitement des véhicules | B9: Restent propriété du concessionnaire. Exploités par la SARL via contrat.
A10: Contrepartie exploitation véhicule | B10: 30 % du prix de chaque course (formule cession) — versé mensuellement
A11: Split revenus course (formule cession) | B11: Chauffeur 40 % · Fonds rachat 10 % · Concessionnaire 30 % · Plateforme 20 %
A12: Split revenus course (formule propriétaire) | B12: Chauffeur 80 % · Plateforme 20 %
A13: Formalité obligatoire OHADA | B13: Commissaire aux apports (apport nature > 5 M) — env. 300-500 k FCFA
A14: Constitution SARL | B14: Une seule AG constitutive avec tous les associés, après phase de collecte 2-3 mois
A15: Phase de collecte (avant constitution) | B15: Protocole d'accord + compte séquestre bancaire
